README.md
pyproject.toml
setup.cfg
setup.py
coaxial/__init__.py
coaxial/api_client.py
coaxial/api_response.py
coaxial/configuration.py
coaxial/exceptions.py
coaxial/py.typed
coaxial/rest.py
coaxial/api/__init__.py
coaxial/api/auth_integration_api.py
coaxial/api/data_integration_api.py
coaxial/api/function_api.py
coaxial/api/model_integration_api.py
coaxial/api/provision_api.py
coaxial/models/__init__.py
coaxial/models/auth_integration.py
coaxial/models/call_model_request.py
coaxial/models/call_model_response.py
coaxial/models/check_access_by_resource_id_request.py
coaxial/models/check_access_for_all_request.py
coaxial/models/dataset.py
coaxial/models/dataset_info.py
coaxial/models/function.py
coaxial/models/grant_access_request.py
coaxial/models/grant_access_response.py
coaxial/models/http_validation_error.py
coaxial/models/integrate_custom_dataset_request.py
coaxial/models/integrate_custom_dataset_response.py
coaxial/models/integrate_custom_model_request.py
coaxial/models/integrate_custom_model_response.py
coaxial/models/integrate_function_request.py
coaxial/models/integrate_function_response.py
coaxial/models/integrate_okta_request.py
coaxial/models/integrate_okta_response.py
coaxial/models/integrate_openai_request.py
coaxial/models/integrate_openai_response.py
coaxial/models/integrate_pinecone_request.py
coaxial/models/integrate_pinecone_response.py
coaxial/models/list_auth_integrations_response.py
coaxial/models/list_data_integrations_response.py
coaxial/models/list_functions_response.py
coaxial/models/list_model_integrations_response.py
coaxial/models/list_users_response.py
coaxial/models/model.py
coaxial/models/pinecone_info.py
coaxial/models/remove_data_integration_request.py
coaxial/models/remove_data_integration_response.py
coaxial/models/remove_function_request.py
coaxial/models/remove_function_response.py
coaxial/models/remove_model_request.py
coaxial/models/remove_model_response.py
coaxial/models/remove_user_request.py
coaxial_python.egg-info/PKG-INFO
coaxial_python.egg-info/SOURCES.txt
coaxial_python.egg-info/dependency_links.txt
coaxial_python.egg-info/requires.txt
coaxial_python.egg-info/top_level.txt